ai/__init__.py
ai/zipline/__init__.py
ai/zipline/group_by.py
ai/zipline/join.py
ai/zipline/logger.py
ai/zipline/query.py
ai/zipline/shorthand.py
ai/zipline/utils.py
ai/zipline/api/__init__.py
ai/zipline/api/constants.py
ai/zipline/api/ttypes.py
ai/zipline/repo/__init__.py
ai/zipline/repo/compile.py
ai/zipline/repo/extract_objects.py
ai/zipline/repo/serializer.py
ai/zipline/repo/teams.py
ai/zipline/repo/validator.py
zipline_ai_dev-0.0.1.data/scripts/compile.py
zipline_ai_dev-0.0.1.dist-info/LICENSE
zipline_ai_dev-0.0.1.dist-info/METADATA
zipline_ai_dev-0.0.1.dist-info/WHEEL
zipline_ai_dev-0.0.1.dist-info/top_level.txt
zipline_ai_dev-0.0.1.dist-info/RECORD
