Metadata-Version: 2.1
Name: zipline-ai-dev
Version: 0.0.1
Summary: Zipline python API library
Home-page: UNKNOWN
License: UNKNOWN
Platform: UNKNOWN
Classifier: Programming Language :: Python :: 3.7
Requires-Python: >=3.7
Requires-Dist: click
Requires-Dist: thrift
